telebot_wrapper/__init__.py
telebot_wrapper/bot.py
telebot_wrapper/utils.py
telebot_wrapper-0.2.0.dist-info/LICENSE
telebot_wrapper-0.2.0.dist-info/METADATA
telebot_wrapper-0.2.0.dist-info/WHEEL
telebot_wrapper-0.2.0.dist-info/RECORD
