Metadata-Version: 2.1
Name: telebot_wrapper
Version: 0.2.0
Summary: pyTelegramBotApi wrapper
Home-page: https://github.com/HamletSargsyan/pyTelegramBotApiWrapper
License: MIT
Keywords: telegram,bot,api,tools
Author: Hamlet
Author-email: hamlets849@gmail.com
Requires-Python: >=3.8,<4.0
Classifier: Development Status :: 5 - Production/Stable
Classifier: Environment :: Console
Classifier: License :: OSI Approved :: MIT License
Classifier: Programming Language :: Python :: 3
Classifier: Programming Language :: Python :: 3.8
Classifier: Programming Language :: Python :: 3.9
Classifier: Programming Language :: Python :: 3.10
Classifier: Programming Language :: Python :: 3.11
Classifier: Programming Language :: Python :: 3.12
Requires-Dist: pyTelegramBotApi (>=4.20.0,<5.0.0)
Project-URL: Repository, https://github.com/HamletSargsyan/pyTelegramBotApiWrapper
